pythonji/__init__.py
pythonji/__main__.py
pythonji_2-0.1.2.dist-info/METADATA
pythonji_2-0.1.2.dist-info/WHEEL
pythonji_2-0.1.2.dist-info/entry_points.txt
pythonji_2-0.1.2.dist-info/licenses/LICENSE
pythonji_2-0.1.2.dist-info/RECORD
