Metadata-Version: 2.1
Name: pythonji-2
Version: 0.1.2
Summary: 🐍 - Write Python with Emojis
Project-URL: Homepage, https://github.com/pavelzw/pythonji-2
Author-email: Geir Arne Hjelle <geirarne@gmail.com>, Pavel Zwerschke <pavelzw@gmail.com>
License: MIT
License-File: LICENSE
Classifier: Programming Language :: Python :: 3
Classifier: Programming Language :: Python :: 3.8
Classifier: Programming Language :: Python :: 3.9
Classifier: Programming Language :: Python :: 3.10
Classifier: Programming Language :: Python :: 3.11
Classifier: Programming Language :: Python :: 3.12
Requires-Python: >=3.8
Requires-Dist: emoji
